halfadder/halfadder.v
//half-adder(半加算器)

//module・・・回路を記述する基本単位
module halfadder(A,B,C,S);
    input A, B;
    output C, S;

//C <- A ^ B;
    assign S = A ^ B;
//S <- A & B;
    assign C = A & B;
    
endmodule

fulladder/fulladder.v
//full-adder
module fulladder(A, B, Cin, Cout, S);
input A,B,Cin;
output Cout, S;
wire C0, C1, S0;

halfadder ha0(A,B,C0,S0);
halfadder ha1(S0,Cin,C1,S);

assign Cout = C0 | C1;

endmodule

fulladder/fulladder_test.v
//simulation
//1. 時間スケールを決める

`timescale 1ns/1ns //1タ　イムスケールあたりの実時間 / 最小単位(丸めの精度)

module fulladder_test;
reg a,b, cin; 
wire cout,s; //出力

parameter STEP = 100; // クロックの時間

fulladder ff(a,b,cin,cout,s); //テストするモジュール

initial begin
            a = 0; b = 0; cin = 0;
    #STEP   a = 0; b = 0; cin = 1;
    #STEP   a = 0; b = 1; cin = 0;
    #STEP   a = 0; b = 1; cin = 1;
    #STEP   a = 1; b = 0; cin = 0;
    #STEP   a = 1; b = 0; cin = 1;
    #STEP   a = 1; b = 1; cin = 0;
    #STEP   a = 1; b = 1; cin = 1;
    #STEP   $finish;
end

initial begin
    $monitor($stime, " a=%b b=%b cin=%b cout=%b s=%b", a, b, cin ,cout, s);
    $dumpfile("fulladder_test.vcd");
    $dumpvars(0, fulladder_test);
end
    
endmodule

fulladder_test.vcd
$date
	Thu Jul  6 06:40:24 2023
$end
$version
	Icarus Verilog
$end
$timescale
	1ns
$end
$scope module fulladder_test $end
$var wire 1 ! s $end
$var wire 1 " cout $end
$var parameter 32 # STEP $end
$var reg 1 $ a $end
$var reg 1 % b $end
$var reg 1 & cin $end
$scope module ff $end
$var wire 1 $ A $end
$var wire 1 % B $end
$var wire 1 & Cin $end
$var wire 1 " Cout $end
$var wire 1 ' S0 $end
$var wire 1 ! S $end
$var wire 1 ( C1 $end
$var wire 1 ) C0 $end
$scope module ha0 $end
$var wire 1 $ A $end
$var wire 1 % B $end
$var wire 1 ) C $end
$var wire 1 ' S $end
$upscope $end
$scope module ha1 $end
$var wire 1 ' A $end
$var wire 1 & B $end
$var wire 1 ( C $end
$var wire 1 ! S $end
$upscope $end
$upscope $end
$upscope $end
$enddefinitions $end
$comment Show the parameter values. $end
$dumpall
b1100100 #
$end
#0
$dumpvars
0)
0(
0'
0&
0%
0$
0"
0!
$end
#100
1!
1&
#200
1'
0&
1%
#300
1"
0!
1(
1&
#400
0"
1!
0(
0&
0%
1$
#500
1"
0!
1(
1&
#600
0(
0'
1)
0&
1%
#700
1!
1&
